feincms_button/__init__.py
feincms_button/appsettings.py
feincms_button/contents.py
feincms_button/models.py
feincms_button/locale/ru/LC_MESSAGES/django.mo
feincms_button/locale/ru/LC_MESSAGES/django.po
feincms_button/templates/content/button/default.html
feincms_button/tests/__init__.py
feincms_button/tests/conftest.py
feincms_button/tests/models.py
feincms_button/tests/settings.py
feincms_button/tests/test_all.py
feincms_button/tests/urls.py
feincms_button/tests/templates/404.html
feincms_button/tests/templates/500.html
feincms_button/tests/templates/base.html
feincms_button-2.0.1.dist-info/LICENSE
feincms_button-2.0.1.dist-info/METADATA
feincms_button-2.0.1.dist-info/WHEEL
feincms_button-2.0.1.dist-info/top_level.txt
feincms_button-2.0.1.dist-info/RECORD
